{"text": ["England", "were", "all", "out", "for", "326", "in", "their", "first", "innings", "on", "the", "second", "day", "of", "the", "third", "and", "final", "test", "against", "Pakistan", "at", "The", "Oval", "on", "Friday", "."], "label": ["B-LOC", "O", "O", "O", "O", "O", "O", "O", "O", "O", "O", "O", "O", "O", "O", "O", "O", "O", "O", "O", "O", "B-LOC", "O", "B-LOC", "I-LOC", "O", "O", "O"]}
{"text": ["At", "a", "hotel", "convention", "here", ",", "the", "party", "associated", "with", "the", "Transcendental", "Meditation", "(", "TM", ")", "movement", "named", "physicist", "John", "Hagelin", "as", "its", "presidential", "nominee", "for", "the", "Nov.", "5", "election", "."], "label": ["O", "O", "O", "O", "O", "O", "O", "O", "O", "O", "O", "B-MISC", "I-MISC", "O", "B-MISC", "O", "O", "O", "O", "B-PER", "I-PER", "O", "O", "O", "O", "O", "O", "O", "O", "O", "O"]}
{"text": ["Shanghai-Ek", "Chor", "is", "jointly", "owned", "by", "the", "Shanghai", "Automobile", "Corporation", "and", "Ek", "Chor", "China", "Motorcycle", "."], "label": ["B-ORG", "I-ORG", "O", "O", "O", "O", "O", "B-ORG", "I-ORG", "I-ORG", "O", "B-ORG", "I-ORG", "I-ORG", "I-ORG", "O"]}
{"text": ["But", "Russian", "President", "Boris", "Yeltsin", "has", "seemed", "unwilling", "to", "meet", "his", "envoy", "and", "went", "on", "holiday", "on", "Monday", "."], "label": ["O", "B-MISC", "O", "B-PER", "I-PER", "O", "O", "O", "O", "O", "O", "O", "O", "O", "O", "O", "O", "O", "O"]}
{"text": ["It", "explained", "the", "\"", "addition", "of", "a", "New", "York", "license", "will", "enable", "Penn", "Treaty", "American", "Corp", "to", "conduct", "business", "in", "all", "50", "states", ",", "following", "the", "company", "'s", "acquisition", "of", "Health", "Insurance", "of", "Vermont", ",", "a", "Vermont", "domiciled", "insurer", ",", "scheduled", "to", "close", "on", "August", "30", ",", "1996", ".", "\""], "label": ["O", "O", "O", "O", "O", "O", "O", "B-LOC", "I-LOC", "O", "O", "O", "B-ORG", "I-ORG", "I-ORG", "I-ORG", "O", "O", "O", "O", "O", "O", "O", "O", "O", "O", "O", "O", "O", "O", "B-ORG", "I-ORG", "I-ORG", "I-ORG", "O", "O", "B-LOC", "O", "O", "O", "O", "O", "O", "O", "O", "O", "O", "O", "O", "O"]}
{"text": ["Leading", "Russian", "shares", "edged", "down", "on", "Wednesday", "in", "thin", "volume", "in", "the", "absence", "of", "Western", "orders", ",", "traders", "said", "."], "label": ["O", "B-MISC", "O", "O", "O", "O", "O", "O", "O", "O", "O", "O", "O", "O", "B-MISC", "O", "O", "O", "O", "O"]}
{"text": ["He", "was", "imprisoned", "for", "four", "years", "in", "1951", "for", "taking", "part", "in", "a", "coup", "attempt", "to", "overthrow", "Peron", "led", "by", "General", "Benjamin", "Menendez", "."], "label": ["O", "O", "O", "O", "O", "O", "O", "O", "O", "O", "O", "O", "O", "O", "O", "O", "O", "B-PER", "O", "O", "O", "B-PER", "I-PER", "O"]}
{"text": ["Jayasuriya", ",", "whose", "first", "50", "included", "three", "sixes", "and", "three", "fours", ",", "went", "on", "to", "an", "unbeaten", "120", "and", "the", "man-of-the-match", "award", "."], "label": ["B-PER", "O", "O", "O", "O", "O", "O", "O", "O", "O", "O", "O", "O", "O", "O", "O", "O", "O", "O", "O", "O", "O", "O"]}
